{
  "2000101516804": {
    "article_id": 2000101516804,
    "article_title": "Kupfer-Gold: Warum auch \u00f6sterreichischer Whisky schmeckt",
    "article_publish_date": "2019-05-21T07:14:45",
    "article_channel": "Lifestyle",
    "article_ressort_name": "Essen & Trinken",
    "total_comments": 184,
    "root_comments": 50,
    "user_threads": [
      {
        "id": 1041830593,
        "parent_id": 0,
        "user_id": 184944,
        "user_name": "quisquis",
        "user_gender": "m",
        "user_created_at": "2010-12-16T15:00:38.707000",
        "comment_headline": "No Headline",
        "comment_text": "Ich trink ja auch keinen Schottischen Marillenbrand.",
        "comment_created_at": "2019-05-21T19:02:36.173000",
        "comment_length": 52,
        "article_id": 2000101516804,
        "article_publish_date": "2019-05-21T07:14:45",
        "article_title": "Kupfer-Gold: Warum auch \u00f6sterreichischer Whisky schmeckt",
        "article_channel": "Lifestyle",
        "article_ressort_name": "Essen & Trinken",
        "replies": [
          {
            "id": 1041839495,
            "parent_id": 1041830593,
            "user_id": 69463,
            "user_name": "Gerry Mander",
            "user_gender": "m",
            "user_created_at": "2001-04-25T10:13:14",
            "comment_headline": "ich schon",
            "comment_text": "wenn er gut ist  das ist das einzige kriterium. qualit\u00e4t.",
            "comment_created_at": "2019-05-21T21:52:27.100000",
            "comment_length": 57,
            "article_id": 2000101516804,
            "article_publish_date": "2019-05-21T07:14:45",
            "article_title": "Kupfer-Gold: Warum auch \u00f6sterreichischer Whisky schmeckt",
            "article_channel": "Lifestyle",
            "article_ressort_name": "Essen & Trinken",
            "replies": []
          }
        ]
      }
    ]
  },
  "2000102336091": {
    "article_id": 2000102336091,
    "article_title": "Semenyas Einspruch gegen Testosteron-Limit abgelehnt",
    "article_publish_date": "2019-05-01T12:21:15",
    "article_channel": "Sport",
    "article_ressort_name": "Leichtathletik ",
    "total_comments": 529,
    "root_comments": 81,
    "user_threads": [
      {
        "id": 1041072216,
        "parent_id": 0,
        "user_id": 503395,
        "user_name": "Georg.Sch\u00fctt",
        "user_gender": "m",
        "user_created_at": "2012-12-29T17:39:08.787000",
        "comment_headline": "Um eine/n Intersex-Athleten nicht zu diskriminieren, werden lieber alle echten Frauen diskriminiert.",
        "comment_text": "Man braucht sich nur die drei Erstplazierten \u00fcber 800 m von Rio anzusehen, um zu wissen, dass hier nicht fair gelaufen wurde.  Sollen die drei doch bei den Jungs mitlaufen!",
        "comment_created_at": "2019-05-01T17:41:41.903000",
        "comment_length": 172,
        "article_id": 2000102336091,
        "article_publish_date": "2019-05-01T12:21:15",
        "article_title": "Semenyas Einspruch gegen Testosteron-Limit abgelehnt",
        "article_channel": "Sport",
        "article_ressort_name": "Leichtathletik ",
        "replies": [
          {
            "id": 1041072517,
            "parent_id": 1041072216,
            "user_id": 603764,
            "user_name": "Sinitintti",
            "user_gender": "w",
            "user_created_at": "2016-11-12T13:06:35.137000",
            "comment_headline": "No Headline",
            "comment_text": "Also ich kenne da Fotos von Marit Bj\u00f6rgen, ob man sich die Frage, ob sie eine \"echte Frau\" ist (ein Begriff aus der Altherrensprache), auch stellen k\u00f6nnte, oder von Kugelsto\u00dferinnen etc., die sind aber tabu, nur afrikanische L\u00e4uferinnen, da traut sich die IAAF. Das Gutachten ist \u00fcbrigens von der Fachwelt zerrissen worden, aber es lieferte das gew\u00fcnschte Ergebnis",
            "comment_created_at": "2019-05-01T17:52:51.630000",
            "comment_length": 364,
            "article_id": 2000102336091,
            "article_publish_date": "2019-05-01T12:21:15",
            "article_title": "Semenyas Einspruch gegen Testosteron-Limit abgelehnt",
            "article_channel": "Sport",
            "article_ressort_name": "Leichtathletik ",
            "replies": [
              {
                "id": 1041074487,
                "parent_id": 1041072517,
                "user_id": 69463,
                "user_name": "Gerry Mander",
                "user_gender": "m",
                "user_created_at": "2001-04-25T10:13:14",
                "comment_headline": "das thema doping wird in den entsprecheden foren behandelt",
                "comment_text": "hier geht es nicht um doping. caster hat weder eierst\u00f6cke noch einen uterus.",
                "comment_created_at": "2019-05-01T18:44:15.083000",
                "comment_length": 76,
                "article_id": 2000102336091,
                "article_publish_date": "2019-05-01T12:21:15",
                "article_title": "Semenyas Einspruch gegen Testosteron-Limit abgelehnt",
                "article_channel": "Sport",
                "article_ressort_name": "Leichtathletik ",
                "replies": [
                  {
                    "id": 1041074816,
                    "parent_id": 1041074487,
                    "user_id": 603764,
                    "user_name": "Sinitintti",
                    "user_gender": "w",
                    "user_created_at": "2016-11-12T13:06:35.137000",
                    "comment_headline": "No Headline",
                    "comment_text": "Was Sie alles wissen. Haben Sie sich l\u00e4ngere Zeit in ihrem Unterleib aufgehalten?",
                    "comment_created_at": "2019-05-01T18:54:45.313000",
                    "comment_length": 81,
                    "article_id": 2000102336091,
                    "article_publish_date": "2019-05-01T12:21:15",
                    "article_title": "Semenyas Einspruch gegen Testosteron-Limit abgelehnt",
                    "article_channel": "Sport",
                    "article_ressort_name": "Leichtathletik ",
                    "replies": [
                      {
                        "id": 1041075523,
                        "parent_id": 1041074816,
                        "user_id": 69463,
                        "user_name": "Gerry Mander",
                        "user_gender": "m",
                        "user_created_at": "2001-04-25T10:13:14",
                        "comment_headline": "nein, ich lese einfach den independent",
                        "comment_text": "und unterlasse normalerweise untergriffe, solange der andere es auch tut, du loser.",
                        "comment_created_at": "2019-05-01T19:19:52.333000",
                        "comment_length": 83,
                        "article_id": 2000102336091,
                        "article_publish_date": "2019-05-01T12:21:15",
                        "article_title": "Semenyas Einspruch gegen Testosteron-Limit abgelehnt",
                        "article_channel": "Sport",
                        "article_ressort_name": "Leichtathletik ",
                        "replies": []
                      }
                    ]
                  }
                ]
              }
            ]
          }
        ]
      }
    ]
  },
  "2000102337910": {
    "article_id": 2000102337910,
    "article_title": "Assange in London zu 50 Wochen Haft verurteilt",
    "article_publish_date": "2019-05-01T13:01:18.060000",
    "article_channel": "International",
    "article_ressort_name": "Geheimdokumente: Wikileaks ",
    "total_comments": 291,
    "root_comments": 79,
    "user_threads": [
      {
        "id": 1041072786,
        "parent_id": 0,
        "user_id": 239635,
        "user_name": "xx2xx",
        "user_gender": "w",
        "user_created_at": "2006-06-07T13:18:26.347000",
        "comment_headline": "Assange tut mir echt Leid.",
        "comment_text": "Was ist das f\u00fcr ein Leben, jahrelang in einer Botschaft de facto eingesperrt, jetzt tats\u00e4chlich eingesperrt - und die dauernde Angst vor der Auslieferung in die USA.  Meiner Meinung nach m\u00fcsste Australien ihn zur\u00fccknehmen und Schutz gew\u00e4hren.   Oder eines unserer feigen EU-L\u00e4nder. Aber die kriechen ja lieber einem Trump hinten rein. Nur ja keine Br\u00f6sel im heiligen und \u00fcber allem stehenden Handel!",
        "comment_created_at": "2019-05-01T17:59:55.050000",
        "comment_length": 399,
        "article_id": 2000102337910,
        "article_publish_date": "2019-05-01T13:01:18.060000",
        "article_title": "Assange in London zu 50 Wochen Haft verurteilt",
        "article_channel": "International",
        "article_ressort_name": "Geheimdokumente: Wikileaks ",
        "replies": [
          {
            "id": 1041073601,
            "parent_id": 1041072786,
            "user_id": 69463,
            "user_name": "Gerry Mander",
            "user_gender": "m",
            "user_created_at": "2001-04-25T10:13:14",
            "comment_headline": "auch die feigen nicht-EU l\u00e4nder nehmen ihn nicht",
            "comment_text": "nicht mal Putin will an dem anstreifen. sonst h\u00e4tte er ihn in seiner botschaft unterschlupf gew\u00e4hrt.",
            "comment_created_at": "2019-05-01T18:21:43.697000",
            "comment_length": 100,
            "article_id": 2000102337910,
            "article_publish_date": "2019-05-01T13:01:18.060000",
            "article_title": "Assange in London zu 50 Wochen Haft verurteilt",
            "article_channel": "International",
            "article_ressort_name": "Geheimdokumente: Wikileaks ",
            "replies": []
          }
        ]
      }
    ]
  },
  "2000102367499": {
    "article_id": 2000102367499,
    "article_title": "Sauer wegen Reklamation: Gastwirt verpr\u00fcgelte vier G\u00e4ste",
    "article_publish_date": "2019-05-02T08:48:42.480000",
    "article_channel": "Panorama",
    "article_ressort_name": "\u00d6sterreich",
    "total_comments": 1377,
    "root_comments": 497,
    "user_threads": [
      {
        "id": 1041091659,
        "parent_id": 0,
        "user_id": 79653,
        "user_name": "Hans der Wedler",
        "user_gender": "m",
        "user_created_at": "2008-09-24T15:10:42.793000",
        "comment_headline": "No Headline",
        "comment_text": "Bin nur wegen den Kommentaren da",
        "comment_created_at": "2019-05-02T11:37:19.090000",
        "comment_length": 32,
        "article_id": 2000102367499,
        "article_publish_date": "2019-05-02T08:48:42.480000",
        "article_title": "Sauer wegen Reklamation: Gastwirt verpr\u00fcgelte vier G\u00e4ste",
        "article_channel": "Panorama",
        "article_ressort_name": "\u00d6sterreich",
        "replies": [
          {
            "id": 1041093040,
            "parent_id": 1041091659,
            "user_id": 69463,
            "user_name": "Gerry Mander",
            "user_gender": "m",
            "user_created_at": "2001-04-25T10:13:14",
            "comment_headline": "wer nicht?",
            "comment_text": "No Comment",
            "comment_created_at": "2019-05-02T12:23:25.540000",
            "comment_length": 10,
            "article_id": 2000102367499,
            "article_publish_date": "2019-05-02T08:48:42.480000",
            "article_title": "Sauer wegen Reklamation: Gastwirt verpr\u00fcgelte vier G\u00e4ste",
            "article_channel": "Panorama",
            "article_ressort_name": "\u00d6sterreich",
            "replies": []
          }
        ]
      }
    ]
  },
  "2000102380774": {
    "article_id": 2000102380774,
    "article_title": "\"Apfelroute\": Apple entz\u00fcndet Logostreit um einen Radweg",
    "article_publish_date": "2019-05-02T12:17:17",
    "article_channel": "Web",
    "article_ressort_name": "Netzpolitik",
    "total_comments": 278,
    "root_comments": 133,
    "user_threads": [
      {
        "id": 1041106099,
        "parent_id": 0,
        "user_id": 554775,
        "user_name": "jojo1109",
        "user_gender": "m",
        "user_created_at": "2015-01-07T01:16:45.647000",
        "comment_headline": "\u00c4pfel werden \u00fcberhaupt eh auch verklagt und verboten",
        "comment_text": "Die darfs gar nicht geben",
        "comment_created_at": "2019-05-02T20:44:00.843000",
        "comment_length": 25,
        "article_id": 2000102380774,
        "article_publish_date": "2019-05-02T12:17:17",
        "article_title": "\"Apfelroute\": Apple entz\u00fcndet Logostreit um einen Radweg",
        "article_channel": "Web",
        "article_ressort_name": "Netzpolitik",
        "replies": [
          {
            "id": 1041109688,
            "parent_id": 1041106099,
            "user_id": 69463,
            "user_name": "Gerry Mander",
            "user_gender": "m",
            "user_created_at": "2001-04-25T10:13:14",
            "comment_headline": "No Headline",
            "comment_text": "vor allem die mit den abgerundeten ecken",
            "comment_created_at": "2019-05-02T23:10:24.807000",
            "comment_length": 40,
            "article_id": 2000102380774,
            "article_publish_date": "2019-05-02T12:17:17",
            "article_title": "\"Apfelroute\": Apple entz\u00fcndet Logostreit um einen Radweg",
            "article_channel": "Web",
            "article_ressort_name": "Netzpolitik",
            "replies": []
          }
        ]
      }
    ]
  },
  "2000102385164": {
    "article_id": 2000102385164,
    "article_title": "Kritik an Semenya-Urteil: \"Als m\u00fcsste Bolt seine Beine k\u00fcrzen\"",
    "article_publish_date": "2019-05-02T12:17:57",
    "article_channel": "Sport",
    "article_ressort_name": "Leichtathletik ",
    "total_comments": 289,
    "root_comments": 95,
    "user_threads": [
      {
        "id": 1041100761,
        "parent_id": 0,
        "user_id": 69463,
        "user_name": "Gerry Mander",
        "user_gender": "m",
        "user_created_at": "2001-04-25T10:13:14",
        "comment_headline": "ein irref\u00fchrender vergleich",
        "comment_text": "\"als m\u00fcsste man Bolt die spritze wegnehmen\", das w\u00e4re der passende vergleich.  oh, wait....",
        "comment_created_at": "2019-05-02T17:05:39.910000",
        "comment_length": 91,
        "article_id": 2000102385164,
        "article_publish_date": "2019-05-02T12:17:57",
        "article_title": "Kritik an Semenya-Urteil: \"Als m\u00fcsste Bolt seine Beine k\u00fcrzen\"",
        "article_channel": "Sport",
        "article_ressort_name": "Leichtathletik ",
        "replies": []
      }
    ]
  },
  "2000102500476": {
    "article_id": 2000102500476,
    "article_title": "USA: China h\u00e4lt \u00fcber eine Million Muslime in \"Konzentrationslagern\"",
    "article_publish_date": "2019-05-04T08:37:11",
    "article_channel": "International",
    "article_ressort_name": "China",
    "total_comments": 347,
    "root_comments": 80,
    "user_threads": [
      {
        "id": 1041147808,
        "parent_id": 0,
        "user_id": 180361,
        "user_name": "sanginius",
        "user_gender": "m",
        "user_created_at": "2007-01-03T16:36:45.343000",
        "comment_headline": "No Headline",
        "comment_text": "genau wie die US Konzentrationslager in denen Hunderttausende Japaner weggesperrt wurden? upsi dar\u00fcber sprechen wir aber lieber nicht",
        "comment_created_at": "2019-05-04T12:29:44.367000",
        "comment_length": 133,
        "article_id": 2000102500476,
        "article_publish_date": "2019-05-04T08:37:11",
        "article_title": "USA: China h\u00e4lt \u00fcber eine Million Muslime in \"Konzentrationslagern\"",
        "article_channel": "International",
        "article_ressort_name": "China",
        "replies": [
          {
            "id": 1041148258,
            "parent_id": 1041147808,
            "user_id": 180916,
            "user_name": "parzenbua",
            "user_gender": "m",
            "user_created_at": "2005-11-10T17:35:45.720000",
            "comment_headline": "No Headline",
            "comment_text": "K\u00f6nnen wir schon. Hat aber nix miteinander zu tun.",
            "comment_created_at": "2019-05-04T12:45:49.850000",
            "comment_length": 50,
            "article_id": 2000102500476,
            "article_publish_date": "2019-05-04T08:37:11",
            "article_title": "USA: China h\u00e4lt \u00fcber eine Million Muslime in \"Konzentrationslagern\"",
            "article_channel": "International",
            "article_ressort_name": "China",
            "replies": [
              {
                "id": 1041150866,
                "parent_id": 1041148258,
                "user_id": 69463,
                "user_name": "Gerry Mander",
                "user_gender": "m",
                "user_created_at": "2001-04-25T10:13:14",
                "comment_headline": "No Headline",
                "comment_text": "aha",
                "comment_created_at": "2019-05-04T14:27:16.780000",
                "comment_length": 3,
                "article_id": 2000102500476,
                "article_publish_date": "2019-05-04T08:37:11",
                "article_title": "USA: China h\u00e4lt \u00fcber eine Million Muslime in \"Konzentrationslagern\"",
                "article_channel": "International",
                "article_ressort_name": "China",
                "replies": []
              }
            ]
          }
        ]
      }
    ]
  },
  "2000102553932": {
    "article_id": 2000102553932,
    "article_title": "B\u00f6rsen wegen drohender Eskalation im US-Zollstreit mit China unter Druck",
    "article_publish_date": "2019-05-05T18:38:26.140000",
    "article_channel": "Wirtschaft",
    "article_ressort_name": "Welthandel",
    "total_comments": 396,
    "root_comments": 87,
    "user_threads": [
      {
        "id": 1041192673,
        "parent_id": 0,
        "user_id": 536826,
        "user_name": "James Z. Kirk",
        "user_gender": "m",
        "user_created_at": "2014-03-10T20:28:49.483000",
        "comment_headline": "dank trump niedrigste arbeitslosenquote seit 50 jahren",
        "comment_text": "No Comment",
        "comment_created_at": "2019-05-06T07:57:22.667000",
        "comment_length": 10,
        "article_id": 2000102553932,
        "article_publish_date": "2019-05-05T18:38:26.140000",
        "article_title": "B\u00f6rsen wegen drohender Eskalation im US-Zollstreit mit China unter Druck",
        "article_channel": "Wirtschaft",
        "article_ressort_name": "Welthandel",
        "replies": [
          {
            "id": 1041193705,
            "parent_id": 1041192673,
            "user_id": 69463,
            "user_name": "Gerry Mander",
            "user_gender": "m",
            "user_created_at": "2001-04-25T10:13:14",
            "comment_headline": "und was passiert jetzt, wenn man den arbeitsmarkt bei vollbesch\u00e4ftigung stimuliert?",
            "comment_text": "No Comment",
            "comment_created_at": "2019-05-06T08:45:27.263000",
            "comment_length": 10,
            "article_id": 2000102553932,
            "article_publish_date": "2019-05-05T18:38:26.140000",
            "article_title": "B\u00f6rsen wegen drohender Eskalation im US-Zollstreit mit China unter Druck",
            "article_channel": "Wirtschaft",
            "article_ressort_name": "Welthandel",
            "replies": []
          }
        ]
      }
    ]
  },
  "2000102662202": {
    "article_id": 2000102662202,
    "article_title": "Proteste tausender Istanbuler gegen Wahlwiederholung",
    "article_publish_date": "2019-05-07T12:10:59.990000",
    "article_channel": "International",
    "article_ressort_name": "T\u00fcrkei",
    "total_comments": 456,
    "root_comments": 171,
    "user_threads": [
      {
        "id": 1041245159,
        "parent_id": 0,
        "user_id": 689914,
        "user_name": "090319",
        "user_gender": "Unknown",
        "user_created_at": "2019-03-25T19:33:48.133000",
        "comment_headline": "Vorbild EU",
        "comment_text": "Vielleicht nimmt sich Erdogan die EU als Vorbild. Der ihre Vorgangsweise ist n\u00e4mlich auch so: Wenn denen das Wahlergebnis nicht passt, dann wird halt so lange und so oft abgestimmt bis das Ergebnis genehm ist.  F\u00fcr mich ist hier kein gro\u00dfer Unterschied zwischen Erdogan und der EU zu sehen. Und was das \u00fcbrige Demokratieverst\u00e4ndnis betrifft, auch nicht.  Die EU als Organisationsgebild hat jedenfalls mit einer Demokratie wenig zu tun. Dort wo es vordergr\u00fcndig so etwas wie den Anschein von Demokratie gibt, werden diese Gremien durch informelle Abkommen, Machtstrukturen (Stichwort: Achse Paris-Berlin) und Absprachen ausgebremst. Zus\u00e4tzlich werkelt in Br\u00fcssel noch eine Armada an Lobbyisten.",
        "comment_created_at": "2019-05-07T16:51:47.730000",
        "comment_length": 693,
        "article_id": 2000102662202,
        "article_publish_date": "2019-05-07T12:10:59.990000",
        "article_title": "Proteste tausender Istanbuler gegen Wahlwiederholung",
        "article_channel": "International",
        "article_ressort_name": "T\u00fcrkei",
        "replies": [
          {
            "id": 1041248635,
            "parent_id": 1041245159,
            "user_id": 69463,
            "user_name": "Gerry Mander",
            "user_gender": "m",
            "user_created_at": "2001-04-25T10:13:14",
            "comment_headline": "dieses uninformierte EU bashing ist einfach unterirdisch",
            "comment_text": "wo werden denn politische gegner der EU massenhaft inhaftiert? wo sind die EU gef\u00e4ngnisse f\u00fcr dissidenten, wo marschiert die EU ein und an wen verkauft die EU waffen?",
            "comment_created_at": "2019-05-07T18:45:20.553000",
            "comment_length": 166,
            "article_id": 2000102662202,
            "article_publish_date": "2019-05-07T12:10:59.990000",
            "article_title": "Proteste tausender Istanbuler gegen Wahlwiederholung",
            "article_channel": "International",
            "article_ressort_name": "T\u00fcrkei",
            "replies": []
          }
        ]
      }
    ]
  },
  "2000102830012": {
    "article_id": 2000102830012,
    "article_title": "Uno-Kritik an \u00f6sterreichischer Asylpolitik fiele heute h\u00e4rter aus",
    "article_publish_date": "2019-05-09T14:36:01",
    "article_channel": "Meinung",
    "article_ressort_name": "Irene Brickner",
    "total_comments": 592,
    "root_comments": 156,
    "user_threads": [
      {
        "id": 1041317718,
        "parent_id": 0,
        "user_id": 76585,
        "user_name": "fr\u00f6hn",
        "user_gender": "w",
        "user_created_at": "2005-06-08T17:45:58.410000",
        "comment_headline": "No Headline",
        "comment_text": "Na, heute scheint der Marschbefehl des Propaganda-Ministeriums offenbar die Frage: \"Was ist mit den anderen L\u00e4ndern ?\" zu sein.",
        "comment_created_at": "2019-05-09T18:10:32.127000",
        "comment_length": 127,
        "article_id": 2000102830012,
        "article_publish_date": "2019-05-09T14:36:01",
        "article_title": "Uno-Kritik an \u00f6sterreichischer Asylpolitik fiele heute h\u00e4rter aus",
        "article_channel": "Meinung",
        "article_ressort_name": "Irene Brickner",
        "replies": [
          {
            "id": 1041319163,
            "parent_id": 1041317718,
            "user_id": 69463,
            "user_name": "Gerry Mander",
            "user_gender": "m",
            "user_created_at": "2001-04-25T10:13:14",
            "comment_headline": "ein beispiel, tagesaktuell aus d\u00e4nemark, einer parlamentarischen demokratie, formell ein k\u00f6nigInnenreich",
            "comment_text": "immer in den spitzenr\u00e4ngen bei human developement index, gini index und bei transparency international zu finden.  heute am amtsgericht in esbjerg: syrischer \"fl\u00fcchtling\" der 17 mal frauen auf den hintern gegriffen hat zu 4 monaten unbedingt verurteilt und permanent ausgewiesen.   https://ekstrabladet.dk/112/udvist-tog-17-kvinder-paa-numsen/7628111",
            "comment_created_at": "2019-05-09T18:55:29.377000",
            "comment_length": 350,
            "article_id": 2000102830012,
            "article_publish_date": "2019-05-09T14:36:01",
            "article_title": "Uno-Kritik an \u00f6sterreichischer Asylpolitik fiele heute h\u00e4rter aus",
            "article_channel": "Meinung",
            "article_ressort_name": "Irene Brickner",
            "replies": []
          }
        ]
      }
    ]
  },
  "2000102882292": {
    "article_id": 2000102882292,
    "article_title": "Gentrifizierung: Die Hipster kommen!",
    "article_publish_date": "2019-05-12T08:00:00",
    "article_channel": "Immobilien",
    "article_ressort_name": "Wohnen in und um Wien",
    "total_comments": 851,
    "root_comments": 157,
    "user_threads": [
      {
        "id": 1041393067,
        "parent_id": 0,
        "user_id": 521269,
        "user_name": "also wirklich nicht",
        "user_gender": "m",
        "user_created_at": "2013-08-05T10:48:18.050000",
        "comment_headline": "No Headline",
        "comment_text": "Absoluter Nonsense-Artikel. Wer volkswirtschaftliche Theorie nur ansatzweise kennt, wird erkenne m\u00fcssen, dass Gentrifizierung grunds\u00e4tzlich positiv zu sehen ist! Aber diese unwissenschaftliche M\u00fcndungsmache w\u00e4re lieber der Stuftung Gurutest \u00fcberlassen worden.",
        "comment_created_at": "2019-05-12T15:36:55.980000",
        "comment_length": 259,
        "article_id": 2000102882292,
        "article_publish_date": "2019-05-12T08:00:00",
        "article_title": "Gentrifizierung: Die Hipster kommen!",
        "article_channel": "Immobilien",
        "article_ressort_name": "Wohnen in und um Wien",
        "replies": [
          {
            "id": 1041393927,
            "parent_id": 1041393067,
            "user_id": 10705,
            "user_name": "anders and",
            "user_gender": "m",
            "user_created_at": "2003-03-21T14:43:52",
            "comment_headline": "No Headline",
            "comment_text": "ist volkswirtschaftliche Theorie denn nicht zu einem guten Teil selbst unwissenschaftliches Guru-Zeugs?",
            "comment_created_at": "2019-05-12T16:03:26.977000",
            "comment_length": 103,
            "article_id": 2000102882292,
            "article_publish_date": "2019-05-12T08:00:00",
            "article_title": "Gentrifizierung: Die Hipster kommen!",
            "article_channel": "Immobilien",
            "article_ressort_name": "Wohnen in und um Wien",
            "replies": [
              {
                "id": 1041396970,
                "parent_id": 1041393927,
                "user_id": 69463,
                "user_name": "Gerry Mander",
                "user_gender": "m",
                "user_created_at": "2001-04-25T10:13:14",
                "comment_headline": "nein, weil ein guru keine theorie im popperschen sinne hat",
                "comment_text": "und sei sie noch so linksliberal.",
                "comment_created_at": "2019-05-12T17:38:47.247000",
                "comment_length": 33,
                "article_id": 2000102882292,
                "article_publish_date": "2019-05-12T08:00:00",
                "article_title": "Gentrifizierung: Die Hipster kommen!",
                "article_channel": "Immobilien",
                "article_ressort_name": "Wohnen in und um Wien",
                "replies": [
                  {
                    "id": 1041397327,
                    "parent_id": 1041396970,
                    "user_id": 10705,
                    "user_name": "anders and",
                    "user_gender": "m",
                    "user_created_at": "2003-03-21T14:43:52",
                    "comment_headline": "No Headline",
                    "comment_text": "die Volkswirtschaftstheorie geht doch zu einem guten Teil von einem nicht existenten Homo \u00d6konomikus aus - was ist daran so popperisch?",
                    "comment_created_at": "2019-05-12T17:50:42.823000",
                    "comment_length": 135,
                    "article_id": 2000102882292,
                    "article_publish_date": "2019-05-12T08:00:00",
                    "article_title": "Gentrifizierung: Die Hipster kommen!",
                    "article_channel": "Immobilien",
                    "article_ressort_name": "Wohnen in und um Wien",
                    "replies": [
                      {
                        "id": 1041469817,
                        "parent_id": 1041397327,
                        "user_id": 69463,
                        "user_name": "Gerry Mander",
                        "user_gender": "m",
                        "user_created_at": "2001-04-25T10:13:14",
                        "comment_headline": "popper lesen",
                        "comment_text": "hilft.",
                        "comment_created_at": "2019-05-14T22:11:45.490000",
                        "comment_length": 6,
                        "article_id": 2000102882292,
                        "article_publish_date": "2019-05-12T08:00:00",
                        "article_title": "Gentrifizierung: Die Hipster kommen!",
                        "article_channel": "Immobilien",
                        "article_ressort_name": "Wohnen in und um Wien",
                        "replies": []
                      }
                    ]
                  }
                ]
              }
            ]
          }
        ]
      }
    ]
  },
  "2000102978853": {
    "article_id": 2000102978853,
    "article_title": "Millionengrab LED-Lampen: In Detroit droht die gro\u00dfe Dunkelheit",
    "article_publish_date": "2019-05-12T13:17:59",
    "article_channel": "Web",
    "article_ressort_name": "Innovationen",
    "total_comments": 352,
    "root_comments": 83,
    "user_threads": [
      {
        "id": 1041390467,
        "parent_id": 0,
        "user_id": 587226,
        "user_name": "Hauptinvestor",
        "user_gender": "m",
        "user_created_at": "2016-07-07T10:00:34.610000",
        "comment_headline": "No Headline",
        "comment_text": "Ich bin immer wieder froh um die wahnsinnigen Fortschritte in der Technik.",
        "comment_created_at": "2019-05-12T13:58:34.470000",
        "comment_length": 74,
        "article_id": 2000102978853,
        "article_publish_date": "2019-05-12T13:17:59",
        "article_title": "Millionengrab LED-Lampen: In Detroit droht die gro\u00dfe Dunkelheit",
        "article_channel": "Web",
        "article_ressort_name": "Innovationen",
        "replies": [
          {
            "id": 1041391940,
            "parent_id": 1041390467,
            "user_id": 69463,
            "user_name": "Gerry Mander",
            "user_gender": "m",
            "user_created_at": "2001-04-25T10:13:14",
            "comment_headline": "postest du von einem Rechenschieber oder einem Kugelrahmen?",
            "comment_text": "No Comment",
            "comment_created_at": "2019-05-12T14:55:49.090000",
            "comment_length": 10,
            "article_id": 2000102978853,
            "article_publish_date": "2019-05-12T13:17:59",
            "article_title": "Millionengrab LED-Lampen: In Detroit droht die gro\u00dfe Dunkelheit",
            "article_channel": "Web",
            "article_ressort_name": "Innovationen",
            "replies": []
          }
        ]
      }
    ]
  },
  "2000103098005": {
    "article_id": 2000103098005,
    "article_title": "Mangelnder Klimaschutz k\u00f6nnte Wirtschaft Billionen kosten",
    "article_publish_date": "2019-05-17T12:42:27",
    "article_channel": "Zukunft",
    "article_ressort_name": "Edition Zukunft",
    "total_comments": 237,
    "root_comments": 53,
    "user_threads": [
      {
        "id": 1041562029,
        "parent_id": 0,
        "user_id": 676496,
        "user_name": "Nikolaus_von_Myra",
        "user_gender": "Unknown",
        "user_created_at": "2018-07-09T11:47:36.610000",
        "comment_headline": "No Headline",
        "comment_text": "Es ist technisch unm\u00f6glich, das Klima vor den Menschen zu sch\u00fctzen.  Zuf\u00e4llige, unbeeinflussbare Sonnen-Eruptionen alle paar Jahre, oder auch Vulkanausbr\u00fcche,  haben erheblich mehr Einfluss auf das Erdklima, als jede noch so gut gemeinte CO-2 Steuer .  Aber mit einer dicken Jacke (bei K\u00e4lte) oder mit Sonnecreme und Badehose (bei Hitze) k\u00f6nnen sich die Menschen zum Gl\u00fcck sehr flexibel vor den meisten klimatischen Bedingungen selber sch\u00fctzen.",
        "comment_created_at": "2019-05-17T15:25:47.580000",
        "comment_length": 444,
        "article_id": 2000103098005,
        "article_publish_date": "2019-05-17T12:42:27",
        "article_title": "Mangelnder Klimaschutz k\u00f6nnte Wirtschaft Billionen kosten",
        "article_channel": "Zukunft",
        "article_ressort_name": "Edition Zukunft",
        "replies": [
          {
            "id": 1041563029,
            "parent_id": 1041562029,
            "user_id": 62021,
            "user_name": "Der auf der Nudelsuppen dahergschwommen is",
            "user_gender": "m",
            "user_created_at": "2007-04-17T12:39:14.337000",
            "comment_headline": "No Headline",
            "comment_text": "Womit erkl\u00e4ren Sie denn den seit Jahren messbaren weltweiten Temperaturanstieg? Sonnen-Eruptionen alle paar Jahre k\u00f6nnen es ja nicht sein, diese m\u00fcssten dazu ja stetig zunehmen. Und hierf\u00fcr gibt es keine Messergebnisse die dies best\u00e4tigen w\u00fcrden. Vulkanausbr\u00fcche also? Ich bitte um eine Auflistung der Vulkanausbr\u00fcche welche eine drastische Zunahme in den letzten Jahrzehnten best\u00e4tigt. Werden Sie ebenso nicht finden. Also bitte, was ist es dann?",
            "comment_created_at": "2019-05-17T16:11:31.267000",
            "comment_length": 447,
            "article_id": 2000103098005,
            "article_publish_date": "2019-05-17T12:42:27",
            "article_title": "Mangelnder Klimaschutz k\u00f6nnte Wirtschaft Billionen kosten",
            "article_channel": "Zukunft",
            "article_ressort_name": "Edition Zukunft",
            "replies": [
              {
                "id": 1041563504,
                "parent_id": 1041563029,
                "user_id": 676496,
                "user_name": "Nikolaus_von_Myra",
                "user_gender": "Unknown",
                "user_created_at": "2018-07-09T11:47:36.610000",
                "comment_headline": "No Headline",
                "comment_text": "Sie haben ja recht, die durch menschliche Industrie bzw. Kfz verursachten Abgase haben ebenfalls ihren Teil dazu beigetragen, dass sich das Klima im Laufe der letzten hundert Jahre erw\u00e4rmt hat. Ich bestreite ja auch nur, dass die Menschheit die technologischen M\u00f6glichkeiten hat, diesen Prozess der Klimaerw\u00e4rmung jetzt auch wieder aktiv umzukehren. Es ist einfach zu sp\u00e4t, das jetzt noch irgendwie \u00e4ndern zu wollen, und eine CO-2 Steuer wird da auch nicht helfen k\u00f6nnen. Jedenfalls f\u00e4nde ich es vern\u00fcnftiger,  dass Menschen ihr Geld f\u00fcr neue Kleidung ausgeben , mit der sie sich besser an die ver\u00e4nderten klimatischen Bedingungen anpassen k\u00f6nnen - anstatt dass man ihnen das Geld unter dem Vorwand einer Co-2 Steuer aus der Tasche zieht.",
                "comment_created_at": "2019-05-17T16:29:56.970000",
                "comment_length": 738,
                "article_id": 2000103098005,
                "article_publish_date": "2019-05-17T12:42:27",
                "article_title": "Mangelnder Klimaschutz k\u00f6nnte Wirtschaft Billionen kosten",
                "article_channel": "Zukunft",
                "article_ressort_name": "Edition Zukunft",
                "replies": [
                  {
                    "id": 1041563709,
                    "parent_id": 1041563504,
                    "user_id": 69463,
                    "user_name": "Gerry Mander",
                    "user_gender": "m",
                    "user_created_at": "2001-04-25T10:13:14",
                    "comment_headline": "wenn sie nicht weiter denken k\u00f6nnen als zu ihrer epidermis",
                    "comment_text": "ist ihr horizont noch begrenzter als ich dachte.",
                    "comment_created_at": "2019-05-17T16:37:06.440000",
                    "comment_length": 48,
                    "article_id": 2000103098005,
                    "article_publish_date": "2019-05-17T12:42:27",
                    "article_title": "Mangelnder Klimaschutz k\u00f6nnte Wirtschaft Billionen kosten",
                    "article_channel": "Zukunft",
                    "article_ressort_name": "Edition Zukunft",
                    "replies": []
                  }
                ]
              }
            ]
          }
        ]
      }
    ]
  },
  "2000103101779": {
    "article_id": 2000103101779,
    "article_title": "Erdo\u011fan wirft Syriens Regime Untergrabung von Idlib-Vereinbarung vor",
    "article_publish_date": "2019-05-14T12:36:42",
    "article_channel": "International",
    "article_ressort_name": "Syrien",
    "total_comments": 34,
    "root_comments": 11,
    "user_threads": [
      {
        "id": 1041458327,
        "parent_id": 0,
        "user_id": 605993,
        "user_name": "Rauschen im Bl\u00e4tterwald",
        "user_gender": "m",
        "user_created_at": "2016-12-28T13:08:37.217000",
        "comment_headline": "Sogar Erdogans Kritik wird im Westen zitiert,",
        "comment_text": "wenn sie gegen Russland und Syrien gerichtet ist.  Der Sultan m\u00f6ge sich zur\u00fcck halten, sonst kann er sich die S-400 aufmalen.",
        "comment_created_at": "2019-05-14T16:52:10.920000",
        "comment_length": 125,
        "article_id": 2000103101779,
        "article_publish_date": "2019-05-14T12:36:42",
        "article_title": "Erdo\u011fan wirft Syriens Regime Untergrabung von Idlib-Vereinbarung vor",
        "article_channel": "International",
        "article_ressort_name": "Syrien",
        "replies": [
          {
            "id": 1041459861,
            "parent_id": 1041458327,
            "user_id": 69463,
            "user_name": "Gerry Mander",
            "user_gender": "m",
            "user_created_at": "2001-04-25T10:13:14",
            "comment_headline": "ach was",
            "comment_text": "pack schl\u00e4gt sich, ...",
            "comment_created_at": "2019-05-14T17:39:17.823000",
            "comment_length": 22,
            "article_id": 2000103101779,
            "article_publish_date": "2019-05-14T12:36:42",
            "article_title": "Erdo\u011fan wirft Syriens Regime Untergrabung von Idlib-Vereinbarung vor",
            "article_channel": "International",
            "article_ressort_name": "Syrien",
            "replies": []
          }
        ]
      }
    ]
  },
  "2000103278431": {
    "article_id": 2000103278431,
    "article_title": "Boris Johnson will Theresa May als Tory-Chef beerben",
    "article_publish_date": "2019-05-16T16:36:08.100000",
    "article_channel": "International",
    "article_ressort_name": "Gro\u00dfbritannien",
    "total_comments": 119,
    "root_comments": 75,
    "user_threads": [
      {
        "id": 1041527888,
        "parent_id": 0,
        "user_id": 654650,
        "user_name": "Objekt-Sinn",
        "user_gender": "Unknown",
        "user_created_at": "2017-12-17T20:25:15.850000",
        "comment_headline": "No Headline",
        "comment_text": "Wie konnte der jemals B\u00fcrgermeister von London werden?",
        "comment_created_at": "2019-05-16T16:45:36.490000",
        "comment_length": 54,
        "article_id": 2000103278431,
        "article_publish_date": "2019-05-16T16:36:08.100000",
        "article_title": "Boris Johnson will Theresa May als Tory-Chef beerben",
        "article_channel": "International",
        "article_ressort_name": "Gro\u00dfbritannien",
        "replies": [
          {
            "id": 1041528549,
            "parent_id": 1041527888,
            "user_id": 69463,
            "user_name": "Gerry Mander",
            "user_gender": "m",
            "user_created_at": "2001-04-25T10:13:14",
            "comment_headline": "No Headline",
            "comment_text": "weil die briten einen speziellen humor haben?",
            "comment_created_at": "2019-05-16T17:05:59.727000",
            "comment_length": 45,
            "article_id": 2000103278431,
            "article_publish_date": "2019-05-16T16:36:08.100000",
            "article_title": "Boris Johnson will Theresa May als Tory-Chef beerben",
            "article_channel": "International",
            "article_ressort_name": "Gro\u00dfbritannien",
            "replies": []
          }
        ]
      }
    ]
  },
  "2000103364196": {
    "article_id": 2000103364196,
    "article_title": "Strache soll Staatsauftr\u00e4ge f\u00fcr Wahlkampfspenden in Aussicht gestellt haben",
    "article_publish_date": "2019-05-17T18:19:06.190000",
    "article_channel": "Inland",
    "article_ressort_name": "FP\u00d6",
    "total_comments": 12042,
    "root_comments": 5473,
    "user_threads": [
      {
        "id": 1041570604,
        "parent_id": 0,
        "user_id": 69463,
        "user_name": "Gerry Mander",
        "user_gender": "m",
        "user_created_at": "2001-04-25T10:13:14",
        "comment_headline": "No Headline",
        "comment_text": "No Comment",
        "comment_created_at": "2019-05-17T20:09:14.770000",
        "comment_length": 10,
        "article_id": 2000103364196,
        "article_publish_date": "2019-05-17T18:19:06.190000",
        "article_title": "Strache soll Staatsauftr\u00e4ge f\u00fcr Wahlkampfspenden in Aussicht gestellt haben",
        "article_channel": "Inland",
        "article_ressort_name": "FP\u00d6",
        "replies": []
      },
      {
        "id": 1041571014,
        "parent_id": 0,
        "user_id": 512315,
        "user_name": "Maecenas81",
        "user_gender": "m",
        "user_created_at": "2012-12-06T09:18:57.057000",
        "comment_headline": "No Headline",
        "comment_text": "Ich frage mich warum so ein Video vor relativ unwichtigen EU Wahlen zugespielt wird und nicht vor den n\u00e4chsten NR Wahlen, wenn man schon so lange zuwartet. Bin gespannt wer dahintersteckt. \u00d6VP selbst, ein ausl\u00e4ndischer Geheimdienst oder Silberstein Kontakte?  Ist schon wie im Film \u201eWag the dog\u201c.",
        "comment_created_at": "2019-05-17T20:16:43.753000",
        "comment_length": 296,
        "article_id": 2000103364196,
        "article_publish_date": "2019-05-17T18:19:06.190000",
        "article_title": "Strache soll Staatsauftr\u00e4ge f\u00fcr Wahlkampfspenden in Aussicht gestellt haben",
        "article_channel": "Inland",
        "article_ressort_name": "FP\u00d6",
        "replies": [
          {
            "id": 1041571336,
            "parent_id": 1041571014,
            "user_id": 69463,
            "user_name": "Gerry Mander",
            "user_gender": "m",
            "user_created_at": "2001-04-25T10:13:14",
            "comment_headline": "na wer soll denn dahinterstehen?",
            "comment_text": "die russen oder die fp\u00f6. sonst war ja niemand zugegen.",
            "comment_created_at": "2019-05-17T20:23:28.857000",
            "comment_length": 54,
            "article_id": 2000103364196,
            "article_publish_date": "2019-05-17T18:19:06.190000",
            "article_title": "Strache soll Staatsauftr\u00e4ge f\u00fcr Wahlkampfspenden in Aussicht gestellt haben",
            "article_channel": "Inland",
            "article_ressort_name": "FP\u00d6",
            "replies": []
          }
        ]
      }
    ]
  },
  "2000103365813": {
    "article_id": 2000103365813,
    "article_title": "Deutscher Satiriker B\u00f6hmermann sprach bereits im April \u00fcber \"Oligarchenvilla auf Ibiza\"",
    "article_publish_date": "2019-05-17T19:00:29.600000",
    "article_channel": "Etat",
    "article_ressort_name": "Medien",
    "total_comments": 1628,
    "root_comments": 463,
    "user_threads": [
      {
        "id": 1041578419,
        "parent_id": 0,
        "user_id": 678357,
        "user_name": "therese vonaufeld",
        "user_gender": "Unknown",
        "user_created_at": "2018-08-14T09:32:17.157000",
        "comment_headline": "No Headline",
        "comment_text": "Als Quelle wird ein westlicher Geheimdienst (Sorge wegen Russland connection) vermutet!",
        "comment_created_at": "2019-05-17T22:55:10.937000",
        "comment_length": 87,
        "article_id": 2000103365813,
        "article_publish_date": "2019-05-17T19:00:29.600000",
        "article_title": "Deutscher Satiriker B\u00f6hmermann sprach bereits im April \u00fcber \"Oligarchenvilla auf Ibiza\"",
        "article_channel": "Etat",
        "article_ressort_name": "Medien",
        "replies": [
          {
            "id": 1041578708,
            "parent_id": 1041578419,
            "user_id": 502577,
            "user_name": "abaris",
            "user_gender": "m",
            "user_created_at": "2008-04-02T15:19:14.817000",
            "comment_headline": "NoNa",
            "comment_text": "Wie ich schon sagte, es war jemand, der sich Zeit nehmen konnte, das richtige strategische Gesp\u00fcr hatte und die n\u00f6tige Breitenwirkung zu erzielen wu\u00dfte.  Medien fallen da ebenso aus wie Parteien. Es war jemand, der den jetzigen Zeitpunkt f\u00fcr richtig erachtete, mit den \u00f6sterreichischen Zust\u00e4nden abzurechnen. Offenbar wurde da grade der Giftschrank ge\u00f6ffnet. Bin neugierig, ob die zu erwartende Kurzsche Relativierung mit einem neuen Video beantwortet wird.",
            "comment_created_at": "2019-05-17T23:00:40.800000",
            "comment_length": 457,
            "article_id": 2000103365813,
            "article_publish_date": "2019-05-17T19:00:29.600000",
            "article_title": "Deutscher Satiriker B\u00f6hmermann sprach bereits im April \u00fcber \"Oligarchenvilla auf Ibiza\"",
            "article_channel": "Etat",
            "article_ressort_name": "Medien",
            "replies": [
              {
                "id": 1041579733,
                "parent_id": 1041578708,
                "user_id": 69463,
                "user_name": "Gerry Mander",
                "user_gender": "m",
                "user_created_at": "2001-04-25T10:13:14",
                "comment_headline": "eine strategie kann ich leider noch nicht erkennen",
                "comment_text": "taktisches gepl\u00e4nkel, strache geht in elternteilzeit, die gaulreiter reiten weiter.",
                "comment_created_at": "2019-05-17T23:26:18.107000",
                "comment_length": 83,
                "article_id": 2000103365813,
                "article_publish_date": "2019-05-17T19:00:29.600000",
                "article_title": "Deutscher Satiriker B\u00f6hmermann sprach bereits im April \u00fcber \"Oligarchenvilla auf Ibiza\"",
                "article_channel": "Etat",
                "article_ressort_name": "Medien",
                "replies": []
              }
            ]
          }
        ]
      }
    ]
  },
  "2000103382950": {
    "article_id": 2000103382950,
    "article_title": "\"Wei\u00dfe Linie am Tisch\": Netz lacht \u00fcber Strache-Memes",
    "article_publish_date": "2019-05-18T10:29:14",
    "article_channel": "Web",
    "article_ressort_name": "Webmix",
    "total_comments": 687,
    "root_comments": 184,
    "user_threads": [
      {
        "id": 1041633332,
        "parent_id": 0,
        "user_id": 85523,
        "user_name": "Hippo Krates",
        "user_gender": "m",
        "user_created_at": "2002-03-13T19:58:43",
        "comment_headline": "Dieser moment, wenn dir auf 4,6km2 (*) ausgerichtet wird, dass du als partei ausg'schi**n hast.",
        "comment_text": "(*) kronenzeitung-auflage: 750.000 750.000 A4-coverseiten \u00e1 (1/16)m2 = ~46.000m2 = 4.6km2 ...was wiederum ausreicht um den gesamten vatikan zehnfach abzudecken.",
        "comment_created_at": "2019-05-18T18:14:45.907000",
        "comment_length": 160,
        "article_id": 2000103382950,
        "article_publish_date": "2019-05-18T10:29:14",
        "article_title": "\"Wei\u00dfe Linie am Tisch\": Netz lacht \u00fcber Strache-Memes",
        "article_channel": "Web",
        "article_ressort_name": "Webmix",
        "replies": [
          {
            "id": 1041648430,
            "parent_id": 1041633332,
            "user_id": 69463,
            "user_name": "Gerry Mander",
            "user_gender": "m",
            "user_created_at": "2001-04-25T10:13:14",
            "comment_headline": "ein quadratkilometer sind eine million quadratmeter",
            "comment_text": "No Comment",
            "comment_created_at": "2019-05-18T21:40:42.720000",
            "comment_length": 10,
            "article_id": 2000103382950,
            "article_publish_date": "2019-05-18T10:29:14",
            "article_title": "\"Wei\u00dfe Linie am Tisch\": Netz lacht \u00fcber Strache-Memes",
            "article_channel": "Web",
            "article_ressort_name": "Webmix",
            "replies": []
          }
        ]
      }
    ]
  },
  "2000103424597": {
    "article_id": 2000103424597,
    "article_title": "Schweizer f\u00fcr sch\u00e4rfere Waffengesetze und gegen Steuerprivilegien",
    "article_publish_date": "2019-05-19T12:48:22",
    "article_channel": "International",
    "article_ressort_name": "Schweiz",
    "total_comments": 147,
    "root_comments": 27,
    "user_threads": [
      {
        "id": 1041678284,
        "parent_id": 0,
        "user_id": 104258,
        "user_name": "HerrACP",
        "user_gender": "m",
        "user_created_at": "2000-10-16T03:04:12",
        "comment_headline": "No Headline",
        "comment_text": "spannened wird es ja immer, wenn solche schweizer volksabstimmung nicht eu-konform ausfallen.",
        "comment_created_at": "2019-05-19T13:20:55.503000",
        "comment_length": 93,
        "article_id": 2000103424597,
        "article_publish_date": "2019-05-19T12:48:22",
        "article_title": "Schweizer f\u00fcr sch\u00e4rfere Waffengesetze und gegen Steuerprivilegien",
        "article_channel": "International",
        "article_ressort_name": "Schweiz",
        "replies": [
          {
            "id": 1041685730,
            "parent_id": 1041678284,
            "user_id": 188754,
            "user_name": "ScottHastings1",
            "user_gender": "m",
            "user_created_at": "2005-06-29T01:26:27.400000",
            "comment_headline": "No Headline",
            "comment_text": "Eigentlich ist es ja recht einfach. Wenn die Schweizer f\u00fcr etwas stimmen, was nicht kompatibel zu den EU-Vertr\u00e4gen ist, m\u00fcssen die sich eben entscheiden, an was ihnen mehr liegt.",
            "comment_created_at": "2019-05-19T16:04:41.803000",
            "comment_length": 178,
            "article_id": 2000103424597,
            "article_publish_date": "2019-05-19T12:48:22",
            "article_title": "Schweizer f\u00fcr sch\u00e4rfere Waffengesetze und gegen Steuerprivilegien",
            "article_channel": "International",
            "article_ressort_name": "Schweiz",
            "replies": [
              {
                "id": 1041687364,
                "parent_id": 1041685730,
                "user_id": 9514,
                "user_name": "Arnold Hau",
                "user_gender": "m",
                "user_created_at": "2004-10-12T18:11:30.740000",
                "comment_headline": "No Headline",
                "comment_text": "Na so einfach ist das nicht. Da steht ja ein riesiges Geb\u00e4ude von Vereinbarungen auf dem Spiel, das letztendlich f\u00fcr die Schweiz notwendig ist weil man sich halt ob man will oder nicht von einem so \u00fcberm\u00e4chtigen \"Partner\" wie der EU nicht isolieren kann wenn man weiterhin wirtschaftlich erfolgreich bleiben will.",
                "comment_created_at": "2019-05-19T16:35:39.713000",
                "comment_length": 313,
                "article_id": 2000103424597,
                "article_publish_date": "2019-05-19T12:48:22",
                "article_title": "Schweizer f\u00fcr sch\u00e4rfere Waffengesetze und gegen Steuerprivilegien",
                "article_channel": "International",
                "article_ressort_name": "Schweiz",
                "replies": [
                  {
                    "id": 1041700114,
                    "parent_id": 1041687364,
                    "user_id": 69463,
                    "user_name": "Gerry Mander",
                    "user_gender": "m",
                    "user_created_at": "2001-04-25T10:13:14",
                    "comment_headline": "eben",
                    "comment_text": "no cherry picking!",
                    "comment_created_at": "2019-05-19T20:25:24.920000",
                    "comment_length": 18,
                    "article_id": 2000103424597,
                    "article_publish_date": "2019-05-19T12:48:22",
                    "article_title": "Schweizer f\u00fcr sch\u00e4rfere Waffengesetze und gegen Steuerprivilegien",
                    "article_channel": "International",
                    "article_ressort_name": "Schweiz",
                    "replies": []
                  }
                ]
              }
            ]
          }
        ]
      }
    ]
  },
  "2000103438743": {
    "article_id": 2000103438743,
    "article_title": "Ex-DFB-Teamspieler \u00d6zil traf sich erneut mit Erdo\u011fan",
    "article_publish_date": "2019-05-19T17:38:13",
    "article_channel": "Sport",
    "article_ressort_name": "Fu\u00dfball International",
    "total_comments": 184,
    "root_comments": 70,
    "user_threads": [
      {
        "id": 1041695867,
        "parent_id": 0,
        "user_id": 577359,
        "user_name": "Marillenkuchen",
        "user_gender": "m",
        "user_created_at": "2016-03-01T07:35:05.767000",
        "comment_headline": "No Headline",
        "comment_text": "Er hat auch schon seine Euros in Lira gewechselt. Brav, Mesut, brav.",
        "comment_created_at": "2019-05-19T19:07:32.320000",
        "comment_length": 68,
        "article_id": 2000103438743,
        "article_publish_date": "2019-05-19T17:38:13",
        "article_title": "Ex-DFB-Teamspieler \u00d6zil traf sich erneut mit Erdo\u011fan",
        "article_channel": "Sport",
        "article_ressort_name": "Fu\u00dfball International",
        "replies": [
          {
            "id": 1041698059,
            "parent_id": 1041695867,
            "user_id": 107583,
            "user_name": "immun man",
            "user_gender": "m",
            "user_created_at": "2002-05-03T09:22:38",
            "comment_headline": "No Headline",
            "comment_text": "Er wird in Pfund bezahlt",
            "comment_created_at": "2019-05-19T19:42:37.493000",
            "comment_length": 24,
            "article_id": 2000103438743,
            "article_publish_date": "2019-05-19T17:38:13",
            "article_title": "Ex-DFB-Teamspieler \u00d6zil traf sich erneut mit Erdo\u011fan",
            "article_channel": "Sport",
            "article_ressort_name": "Fu\u00dfball International",
            "replies": [
              {
                "id": 1041698469,
                "parent_id": 1041698059,
                "user_id": 69463,
                "user_name": "Gerry Mander",
                "user_gender": "m",
                "user_created_at": "2001-04-25T10:13:14",
                "comment_headline": "hoffentlich hat er nicht alle seine euros von fr\u00fcher in pfund gewechselt",
                "comment_text": "erst in britische pfund gewechselt und dann in t\u00fcrkische pfund. als n\u00e4chstes wartet dann wirklich die oben besungene br\u00fccke.",
                "comment_created_at": "2019-05-19T19:51:33.047000",
                "comment_length": 124,
                "article_id": 2000103438743,
                "article_publish_date": "2019-05-19T17:38:13",
                "article_title": "Ex-DFB-Teamspieler \u00d6zil traf sich erneut mit Erdo\u011fan",
                "article_channel": "Sport",
                "article_ressort_name": "Fu\u00dfball International",
                "replies": []
              }
            ]
          }
        ]
      },
      {
        "id": 1041693693,
        "parent_id": 0,
        "user_id": 22680,
        "user_name": "Cannondale27",
        "user_gender": "m",
        "user_created_at": "2009-04-09T11:40:50.733000",
        "comment_headline": "In manchen L\u00e4ndern....",
        "comment_text": "...sollte man sich mehr interessieren, mit welchen Leuten sich Mitglieder ihrer Regierung so treffen...  ...anstatt sich um Privatbesuche ehemaliger deutscher Nationalspieler bei einem Regierungsmitglied des Herkunftlandes seiner Eltern zu \"k\u00fcmmern\"!  Mei oh mei...",
        "comment_created_at": "2019-05-19T18:31:03.110000",
        "comment_length": 265,
        "article_id": 2000103438743,
        "article_publish_date": "2019-05-19T17:38:13",
        "article_title": "Ex-DFB-Teamspieler \u00d6zil traf sich erneut mit Erdo\u011fan",
        "article_channel": "Sport",
        "article_ressort_name": "Fu\u00dfball International",
        "replies": [
          {
            "id": 1041698872,
            "parent_id": 1041693693,
            "user_id": 69463,
            "user_name": "Gerry Mander",
            "user_gender": "m",
            "user_created_at": "2001-04-25T10:13:14",
            "comment_headline": "die zeitung ist voll von diesen treffen unserer \"regierungsmitglieder\"",
            "comment_text": "da stehen 5 artikel dar\u00fcber \u00fcber diesem einen mit \u00d6zil. man scheint sich also bereits \"mehr\" daf\u00fcr zu interessieren, was man auch an der anzahl der postings ablesen kann. worauf genau wollten sie also hinweisen?",
            "comment_created_at": "2019-05-19T19:59:35.790000",
            "comment_length": 211,
            "article_id": 2000103438743,
            "article_publish_date": "2019-05-19T17:38:13",
            "article_title": "Ex-DFB-Teamspieler \u00d6zil traf sich erneut mit Erdo\u011fan",
            "article_channel": "Sport",
            "article_ressort_name": "Fu\u00dfball International",
            "replies": []
          }
        ]
      }
    ]
  },
  "2000103489586": {
    "article_id": 2000103489586,
    "article_title": "\"Kein Spekulationsobjekt\": Strache wollte Trinkwasser 2013 noch sch\u00fctzen",
    "article_publish_date": "2019-05-20T16:16:05",
    "article_channel": "Wirtschaft",
    "article_ressort_name": "Wirtschaftspolitik",
    "total_comments": 299,
    "root_comments": 121,
    "user_threads": [
      {
        "id": 1041756305,
        "parent_id": 0,
        "user_id": 241781,
        "user_name": "BerufsSkeptiker",
        "user_gender": "m",
        "user_created_at": "2012-02-28T16:01:23.440000",
        "comment_headline": "Im Wikipedia-Artikel zu \"Wei\u00dfes Gold\" werden angef\u00fchrt:",
        "comment_text": "Marmor, Porzellan, Silber, Kreide, Borax, Elfenbein, Papier, Angora, Baumwolle, Kokain, Methanhydrat, Zucker, Spargel, Salz, Bryndza. Wasser ist nicht darunter.",
        "comment_created_at": "2019-05-20T16:57:17.193000",
        "comment_length": 160,
        "article_id": 2000103489586,
        "article_publish_date": "2019-05-20T16:16:05",
        "article_title": "\"Kein Spekulationsobjekt\": Strache wollte Trinkwasser 2013 noch sch\u00fctzen",
        "article_channel": "Wirtschaft",
        "article_ressort_name": "Wirtschaftspolitik",
        "replies": [
          {
            "id": 1041758203,
            "parent_id": 1041756305,
            "user_id": 69463,
            "user_name": "Gerry Mander",
            "user_gender": "m",
            "user_created_at": "2001-04-25T10:13:14",
            "comment_headline": "na dann klicken sie mal den artikel \u00fcber HC Strache an",
            "comment_text": "dort steht ja auch nichts \u00fcber intelligenz.",
            "comment_created_at": "2019-05-20T17:26:05.237000",
            "comment_length": 43,
            "article_id": 2000103489586,
            "article_publish_date": "2019-05-20T16:16:05",
            "article_title": "\"Kein Spekulationsobjekt\": Strache wollte Trinkwasser 2013 noch sch\u00fctzen",
            "article_channel": "Wirtschaft",
            "article_ressort_name": "Wirtschaftspolitik",
            "replies": []
          }
        ]
      }
    ]
  },
  "2000103509510": {
    "article_id": 2000103509510,
    "article_title": "Johann Gudenus: Der engste Vertraute ist Straches Sargnagel",
    "article_publish_date": "2019-05-21T06:00:00",
    "article_channel": "Panorama",
    "article_ressort_name": "Wiener Rathaus",
    "total_comments": 961,
    "root_comments": 362,
    "user_threads": [
      {
        "id": 1041819074,
        "parent_id": 0,
        "user_id": 69463,
        "user_name": "Gerry Mander",
        "user_gender": "m",
        "user_created_at": "2001-04-25T10:13:14",
        "comment_headline": "jeder satisfaktionsf\u00e4hige rechte (mit anstand) w\u00fcsste was jetzt zu tun ist,",
        "comment_text": "aber leider haben sie keinen anstand mehr. so sad!  unser wasser f\u00fcr die russen. das werden wir euch nie vergessen.",
        "comment_created_at": "2019-05-21T15:33:43.053000",
        "comment_length": 115,
        "article_id": 2000103509510,
        "article_publish_date": "2019-05-21T06:00:00",
        "article_title": "Johann Gudenus: Der engste Vertraute ist Straches Sargnagel",
        "article_channel": "Panorama",
        "article_ressort_name": "Wiener Rathaus",
        "replies": []
      }
    ]
  },
  "2000103578928": {
    "article_id": 2000103578928,
    "article_title": "Ibiza-Video: Gudenus bef\u00fcrchtet weiteres Material und \u00e4u\u00dfert Verdacht auf K.-o.-Tropfen",
    "article_publish_date": "2019-05-21T17:30:11",
    "article_channel": "Panorama",
    "article_ressort_name": "Wien",
    "total_comments": 1654,
    "root_comments": 917,
    "user_threads": [
      {
        "id": 1041836460,
        "parent_id": 0,
        "user_id": 69463,
        "user_name": "Gerry Mander",
        "user_gender": "m",
        "user_created_at": "2001-04-25T10:13:14",
        "comment_headline": "wir h\u00e4tten dir ja alles verziehen, das koks, die huren, die freih\u00e4ndige auftragsvergabe,  die l\u00fcgen",
        "comment_text": "aber niemals h\u00e4tten wir dir vergeben \"unser wasser\" an die russen zu verkaufen...",
        "comment_created_at": "2019-05-21T20:43:06.403000",
        "comment_length": 81,
        "article_id": 2000103578928,
        "article_publish_date": "2019-05-21T17:30:11",
        "article_title": "Ibiza-Video: Gudenus bef\u00fcrchtet weiteres Material und \u00e4u\u00dfert Verdacht auf K.-o.-Tropfen",
        "article_channel": "Panorama",
        "article_ressort_name": "Wien",
        "replies": []
      },
      {
        "id": 1041838183,
        "parent_id": 0,
        "user_id": 69463,
        "user_name": "Gerry Mander",
        "user_gender": "m",
        "user_created_at": "2001-04-25T10:13:14",
        "comment_headline": "red bull mit alles - und scharf",
        "comment_text": "sozusagen. wer psychotrope substanzen konsumiert kommt ins arbeitslager und wird anschlie\u00dfend ausgewiesen.   right?",
        "comment_created_at": "2019-05-21T21:23:04.407000",
        "comment_length": 115,
        "article_id": 2000103578928,
        "article_publish_date": "2019-05-21T17:30:11",
        "article_title": "Ibiza-Video: Gudenus bef\u00fcrchtet weiteres Material und \u00e4u\u00dfert Verdacht auf K.-o.-Tropfen",
        "article_channel": "Panorama",
        "article_ressort_name": "Wien",
        "replies": []
      }
    ]
  },
  "2000103644730": {
    "article_id": 2000103644730,
    "article_title": "Der Oligarch, der in Ibiza zum Handkuss kam",
    "article_publish_date": "2019-05-23T06:00:00",
    "article_channel": "Wirtschaft",
    "article_ressort_name": "Wirtschaftspolitik",
    "total_comments": 224,
    "root_comments": 74,
    "user_threads": [
      {
        "id": 1041898296,
        "parent_id": 0,
        "user_id": 7952,
        "user_name": "ahmet hoca c\u00fcbbeli",
        "user_gender": "m",
        "user_created_at": "2007-04-03T13:31:19.497000",
        "comment_headline": "No Headline",
        "comment_text": "Itera ist kein Palindrom zu Ateri",
        "comment_created_at": "2019-05-23T07:28:55.787000",
        "comment_length": 33,
        "article_id": 2000103644730,
        "article_publish_date": "2019-05-23T06:00:00",
        "article_title": "Der Oligarch, der in Ibiza zum Handkuss kam",
        "article_channel": "Wirtschaft",
        "article_ressort_name": "Wirtschaftspolitik",
        "replies": [
          {
            "id": 1041899121,
            "parent_id": 1041898296,
            "user_id": 167203,
            "user_name": "Not A. MS Troll",
            "user_gender": "m",
            "user_created_at": "2002-02-08T14:58:03",
            "comment_headline": "No Headline",
            "comment_text": "Nein?",
            "comment_created_at": "2019-05-23T07:59:42.803000",
            "comment_length": 5,
            "article_id": 2000103644730,
            "article_publish_date": "2019-05-23T06:00:00",
            "article_title": "Der Oligarch, der in Ibiza zum Handkuss kam",
            "article_channel": "Wirtschaft",
            "article_ressort_name": "Wirtschaftspolitik",
            "replies": [
              {
                "id": 1041900164,
                "parent_id": 1041899121,
                "user_id": 69463,
                "user_name": "Gerry Mander",
                "user_gender": "m",
                "user_created_at": "2001-04-25T10:13:14",
                "comment_headline": "nein, das palindrom w\u00e4re Ireta",
                "comment_text": "No Comment",
                "comment_created_at": "2019-05-23T08:30:47.513000",
                "comment_length": 10,
                "article_id": 2000103644730,
                "article_publish_date": "2019-05-23T06:00:00",
                "article_title": "Der Oligarch, der in Ibiza zum Handkuss kam",
                "article_channel": "Wirtschaft",
                "article_ressort_name": "Wirtschaftspolitik",
                "replies": []
              }
            ]
          }
        ]
      }
    ]
  },
  "2000103686053": {
    "article_id": 2000103686053,
    "article_title": "Quelle illegalen FCKW-Aussto\u00dfes in Ostchina lokalisiert",
    "article_publish_date": "2019-05-23T14:53:00",
    "article_channel": "Wissenschaft",
    "article_ressort_name": "Natur",
    "total_comments": 191,
    "root_comments": 47,
    "user_threads": [
      {
        "id": 1041921914,
        "parent_id": 0,
        "user_id": 634111,
        "user_name": "Verena K.",
        "user_gender": "Unknown",
        "user_created_at": "2017-06-09T09:02:42.317000",
        "comment_headline": "No Headline",
        "comment_text": "jeden Betrieb kontrollieren Verbecher einsperren, das ist kein Witz",
        "comment_created_at": "2019-05-23T16:39:41.580000",
        "comment_length": 67,
        "article_id": 2000103686053,
        "article_publish_date": "2019-05-23T14:53:00",
        "article_title": "Quelle illegalen FCKW-Aussto\u00dfes in Ostchina lokalisiert",
        "article_channel": "Wissenschaft",
        "article_ressort_name": "Natur",
        "replies": [
          {
            "id": 1041925127,
            "parent_id": 1041921914,
            "user_id": 534149,
            "user_name": "georgelser.blogsport.at",
            "user_gender": "m",
            "user_created_at": "2014-02-06T10:02:15.837000",
            "comment_headline": "No Headline",
            "comment_text": "Wwnn's darum geht, mache ich mir bei China keine Sorgen.",
            "comment_created_at": "2019-05-23T17:46:35.713000",
            "comment_length": 56,
            "article_id": 2000103686053,
            "article_publish_date": "2019-05-23T14:53:00",
            "article_title": "Quelle illegalen FCKW-Aussto\u00dfes in Ostchina lokalisiert",
            "article_channel": "Wissenschaft",
            "article_ressort_name": "Natur",
            "replies": [
              {
                "id": 1041927655,
                "parent_id": 1041925127,
                "user_id": 69463,
                "user_name": "Gerry Mander",
                "user_gender": "m",
                "user_created_at": "2001-04-25T10:13:14",
                "comment_headline": "die chinesiche KP kann  keiner einsperren",
                "comment_text": "No Comment",
                "comment_created_at": "2019-05-23T18:48:28.250000",
                "comment_length": 10,
                "article_id": 2000103686053,
                "article_publish_date": "2019-05-23T14:53:00",
                "article_title": "Quelle illegalen FCKW-Aussto\u00dfes in Ostchina lokalisiert",
                "article_channel": "Wissenschaft",
                "article_ressort_name": "Natur",
                "replies": []
              }
            ]
          }
        ]
      }
    ]
  },
  "2000103729062": {
    "article_id": 2000103729062,
    "article_title": "Stau am Everest: Zwei weitere Bergsteiger ums Leben gekommen",
    "article_publish_date": "2019-05-24T07:40:37.710000",
    "article_channel": "Panorama",
    "article_ressort_name": "Welt-Chronik",
    "total_comments": 979,
    "root_comments": 405,
    "user_threads": [
      {
        "id": 1041993688,
        "parent_id": 0,
        "user_id": 211573,
        "user_name": "Semmerl",
        "user_gender": "m",
        "user_created_at": "2003-04-17T07:50:01",
        "comment_headline": "Everest zusperren - JETZT!",
        "comment_text": "No Comment",
        "comment_created_at": "2019-05-25T13:42:00.707000",
        "comment_length": 10,
        "article_id": 2000103729062,
        "article_publish_date": "2019-05-24T07:40:37.710000",
        "article_title": "Stau am Everest: Zwei weitere Bergsteiger ums Leben gekommen",
        "article_channel": "Panorama",
        "article_ressort_name": "Welt-Chronik",
        "replies": [
          {
            "id": 1041994438,
            "parent_id": 1041993688,
            "user_id": 69463,
            "user_name": "Gerry Mander",
            "user_gender": "m",
            "user_created_at": "2001-04-25T10:13:14",
            "comment_headline": "Everexit?",
            "comment_text": "No Comment",
            "comment_created_at": "2019-05-25T14:15:22.553000",
            "comment_length": 10,
            "article_id": 2000103729062,
            "article_publish_date": "2019-05-24T07:40:37.710000",
            "article_title": "Stau am Everest: Zwei weitere Bergsteiger ums Leben gekommen",
            "article_channel": "Panorama",
            "article_ressort_name": "Welt-Chronik",
            "replies": []
          }
        ]
      }
    ]
  },
  "2000103772732": {
    "article_id": 2000103772732,
    "article_title": "Millionen Kubikmeter Schadholz: Hundestaffel jagt gefr\u00e4\u00dfige K\u00e4fer",
    "article_publish_date": "2019-05-26T09:00:00",
    "article_channel": "Wirtschaft",
    "article_ressort_name": "Unternehmen",
    "total_comments": 27,
    "root_comments": 10,
    "user_threads": [
      {
        "id": 1042014211,
        "parent_id": 0,
        "user_id": 603257,
        "user_name": "kONTRA4U",
        "user_gender": "m",
        "user_created_at": "2016-11-04T13:49:16.713000",
        "comment_headline": "o.\u00d6",
        "comment_text": "Also mein Wuffi w\u00fcrde wegrennen wenn er so eine Laubholzbockk\u00e4ferlarve sehen w\u00fcrde ggg",
        "comment_created_at": "2019-05-26T11:26:16.213000",
        "comment_length": 86,
        "article_id": 2000103772732,
        "article_publish_date": "2019-05-26T09:00:00",
        "article_title": "Millionen Kubikmeter Schadholz: Hundestaffel jagt gefr\u00e4\u00dfige K\u00e4fer",
        "article_channel": "Wirtschaft",
        "article_ressort_name": "Unternehmen",
        "replies": [
          {
            "id": 1042016305,
            "parent_id": 1042014211,
            "user_id": 563338,
            "user_name": "Austrobalkanist",
            "user_gender": "m",
            "user_created_at": "2015-06-18T21:39:56.750000",
            "comment_headline": "No Headline",
            "comment_text": "Zwergpinscherm\u00e4nnchen?",
            "comment_created_at": "2019-05-26T12:18:52.577000",
            "comment_length": 22,
            "article_id": 2000103772732,
            "article_publish_date": "2019-05-26T09:00:00",
            "article_title": "Millionen Kubikmeter Schadholz: Hundestaffel jagt gefr\u00e4\u00dfige K\u00e4fer",
            "article_channel": "Wirtschaft",
            "article_ressort_name": "Unternehmen",
            "replies": [
              {
                "id": 1042049674,
                "parent_id": 1042016305,
                "user_id": 69463,
                "user_name": "Gerry Mander",
                "user_gender": "m",
                "user_created_at": "2001-04-25T10:13:14",
                "comment_headline": "golden retriever!",
                "comment_text": "der ist auch gegen einbrecher super. er hinterl\u00e4sst auf dem einbrecher speichelspuren und sollte man den einbrecher zeitnah fassen, ist er anhand der speichelspuren (vom abschlecken) eindeutig zu identifizieren.",
                "comment_created_at": "2019-05-26T22:51:01.887000",
                "comment_length": 211,
                "article_id": 2000103772732,
                "article_publish_date": "2019-05-26T09:00:00",
                "article_title": "Millionen Kubikmeter Schadholz: Hundestaffel jagt gefr\u00e4\u00dfige K\u00e4fer",
                "article_channel": "Wirtschaft",
                "article_ressort_name": "Unternehmen",
                "replies": []
              }
            ]
          }
        ]
      }
    ]
  },
  "2000103842155": {
    "article_id": 2000103842155,
    "article_title": "F\u00fcr Kickl Verbindungen zwischen BVT und Ibiza-Video m\u00f6glich",
    "article_publish_date": "2019-05-26T17:11:18",
    "article_channel": "Panorama",
    "article_ressort_name": "\u00d6sterreich",
    "total_comments": 197,
    "root_comments": 55,
    "user_threads": [
      {
        "id": 1042045355,
        "parent_id": 0,
        "user_id": 651613,
        "user_name": "stachligerose",
        "user_gender": "Unknown",
        "user_created_at": "2017-10-26T10:11:00.447000",
        "comment_headline": "No Headline",
        "comment_text": "Ich wei\u00df nicht, wer dieses Viedeo in Auftrag gegeben hat, aber es war auf jeden Fall gut zu sehen, wie der Strache \u00d6sterreich als sein pers\u00f6nliches Eigentum sieht.Der wollte echt unser Trinkwasser an irgendwelche Russen verkaufen. Echt jetzt, hatte er vor.",
        "comment_created_at": "2019-05-26T21:23:51.373000",
        "comment_length": 256,
        "article_id": 2000103842155,
        "article_publish_date": "2019-05-26T17:11:18",
        "article_title": "F\u00fcr Kickl Verbindungen zwischen BVT und Ibiza-Video m\u00f6glich",
        "article_channel": "Panorama",
        "article_ressort_name": "\u00d6sterreich",
        "replies": [
          {
            "id": 1042048065,
            "parent_id": 1042045355,
            "user_id": 507904,
            "user_name": "Rohlingsspindel",
            "user_gender": "m",
            "user_created_at": "2003-01-27T17:48:05",
            "comment_headline": "No Headline",
            "comment_text": "ich m\u00f6chte Strache wirklich nicht verteidigen.  Unser Trinkwasser wollten aber auch schon andere verscherbeln.",
            "comment_created_at": "2019-05-26T22:19:01.607000",
            "comment_length": 110,
            "article_id": 2000103842155,
            "article_publish_date": "2019-05-26T17:11:18",
            "article_title": "F\u00fcr Kickl Verbindungen zwischen BVT und Ibiza-Video m\u00f6glich",
            "article_channel": "Panorama",
            "article_ressort_name": "\u00d6sterreich",
            "replies": [
              {
                "id": 1042050266,
                "parent_id": 1042048065,
                "user_id": 69463,
                "user_name": "Gerry Mander",
                "user_gender": "m",
                "user_created_at": "2001-04-25T10:13:14",
                "comment_headline": "sicher. aber kaum leute die vorher kundtaten, dass die\" EU\" unser wasser an dunkle m\u00e4chte verkaufen will",
                "comment_text": "w\u00e4hrend sie selber eben diesem treiben als letzte bastion entgegenstehen w\u00fcrden.",
                "comment_created_at": "2019-05-26T23:01:19.003000",
                "comment_length": 80,
                "article_id": 2000103842155,
                "article_publish_date": "2019-05-26T17:11:18",
                "article_title": "F\u00fcr Kickl Verbindungen zwischen BVT und Ibiza-Video m\u00f6glich",
                "article_channel": "Panorama",
                "article_ressort_name": "\u00d6sterreich",
                "replies": []
              }
            ]
          }
        ]
      }
    ]
  },
  "2000103948806": {
    "article_id": 2000103948806,
    "article_title": "Rendite griechischer Anleihen auf Rekordtief",
    "article_publish_date": "2019-05-28T10:52:53",
    "article_channel": "Wirtschaft",
    "article_ressort_name": "Finanzen & B\u00f6rse",
    "total_comments": 29,
    "root_comments": 10,
    "user_threads": [
      {
        "id": 1042141877,
        "parent_id": 0,
        "user_id": 499562,
        "user_name": "betterknower",
        "user_gender": "m",
        "user_created_at": "2011-04-04T11:56:14.797000",
        "comment_headline": "3,23 % sind nicht schlecht",
        "comment_text": "f\u00fcr risikolose Anleihen, die nicht mit Eigenkapital unterlegt werden m\u00fcssen. Die Banken wissen eh nicht, wo sie ihr Geld sinnvoll anlegen sollen",
        "comment_created_at": "2019-05-28T12:21:35.247000",
        "comment_length": 144,
        "article_id": 2000103948806,
        "article_publish_date": "2019-05-28T10:52:53",
        "article_title": "Rendite griechischer Anleihen auf Rekordtief",
        "article_channel": "Wirtschaft",
        "article_ressort_name": "Finanzen & B\u00f6rse",
        "replies": [
          {
            "id": 1042143661,
            "parent_id": 1042141877,
            "user_id": 693695,
            "user_name": "Sattelitenauge",
            "user_gender": "Unknown",
            "user_created_at": "2019-05-24T20:56:33.963000",
            "comment_headline": "No Headline",
            "comment_text": "Ja, v\u00f6llig durchgeknallt.  Die Banken holen sich f\u00fcr 0,0% Zinsen die Billionen von der EZB. Dann \u201ekaufen\u201c die mit den \u201eGeldern\u201c Staatsanleihen mit Zinss\u00e4tzen von 0,5 bis \u00fcber 3%. Mit 2% von jeder Billion f\u00fcttert die EZB die Banken dann mit 20.000 Mio. Euro pro Jahr.   Die Amerikaner machen es nicht so bl\u00f6d, lassen die Notenbank direkt Staatsanleihen \u00fcbernehmen. Dort geht das gesch\u00f6pfte Geld auch vorwiegend in den Konsum und baut sich nicht in irrealen Bilanzsummen der Banken auf.",
            "comment_created_at": "2019-05-28T12:59:33.393000",
            "comment_length": 484,
            "article_id": 2000103948806,
            "article_publish_date": "2019-05-28T10:52:53",
            "article_title": "Rendite griechischer Anleihen auf Rekordtief",
            "article_channel": "Wirtschaft",
            "article_ressort_name": "Finanzen & B\u00f6rse",
            "replies": [
              {
                "id": 1042150977,
                "parent_id": 1042143661,
                "user_id": 69463,
                "user_name": "Gerry Mander",
                "user_gender": "m",
                "user_created_at": "2001-04-25T10:13:14",
                "comment_headline": "tja, dort geht das gesch\u00f6pfte geld direkt in den konsum",
                "comment_text": "und damit grossteils nach china. super strategie.",
                "comment_created_at": "2019-05-28T15:07:16.703000",
                "comment_length": 49,
                "article_id": 2000103948806,
                "article_publish_date": "2019-05-28T10:52:53",
                "article_title": "Rendite griechischer Anleihen auf Rekordtief",
                "article_channel": "Wirtschaft",
                "article_ressort_name": "Finanzen & B\u00f6rse",
                "replies": []
              }
            ]
          }
        ]
      }
    ]
  },
  "2000103960808": {
    "article_id": 2000103960808,
    "article_title": "\"S\u00fcddeutsche Zeitung\" und \"Spiegel\" wegen Ibiza-Video angezeigt",
    "article_publish_date": "2019-05-28T12:14:43",
    "article_channel": "Panorama",
    "article_ressort_name": "\u00d6sterreich",
    "total_comments": 962,
    "root_comments": 267,
    "user_threads": [
      {
        "id": 1042159099,
        "parent_id": 0,
        "user_id": 685775,
        "user_name": "mrs.robinson",
        "user_gender": "Unknown",
        "user_created_at": "2019-01-08T14:05:08.873000",
        "comment_headline": "No Headline",
        "comment_text": "Faktum ist und bleibt: Jemanden ohne seine Zustimmung bzw. heimlich zu filmen, ist ein gravierender Eingriff in fundamentale Grundrechte! - Dass dies ernsthaft von so vielen hier in Frage gestellt wird, ist fragw\u00fcrdig und beunruhigend.  Wer so einen Rechtsbruch grunds\u00e4tzlich bef\u00fcrwortet, blendet aus, dass er/sie morgen schon der/die N\u00e4chste sein kann...",
        "comment_created_at": "2019-05-28T18:18:05.283000",
        "comment_length": 355,
        "article_id": 2000103960808,
        "article_publish_date": "2019-05-28T12:14:43",
        "article_title": "\"S\u00fcddeutsche Zeitung\" und \"Spiegel\" wegen Ibiza-Video angezeigt",
        "article_channel": "Panorama",
        "article_ressort_name": "\u00d6sterreich",
        "replies": [
          {
            "id": 1042159522,
            "parent_id": 1042159099,
            "user_id": 675788,
            "user_name": "KRW_Leaf",
            "user_gender": "Unknown",
            "user_created_at": "2018-06-24T21:00:27.423000",
            "comment_headline": "Einen Mord d\u00fcrfte man also auch nicht aufnehmen",
            "comment_text": "weil man in die Grundrechte des M\u00f6rders eingreift?  Bei aller \"Heldenverehrung\" d\u00fcrfen Sie gerne etwas NACHDENKEN vor dem posten.",
            "comment_created_at": "2019-05-28T18:29:10.030000",
            "comment_length": 129,
            "article_id": 2000103960808,
            "article_publish_date": "2019-05-28T12:14:43",
            "article_title": "\"S\u00fcddeutsche Zeitung\" und \"Spiegel\" wegen Ibiza-Video angezeigt",
            "article_channel": "Panorama",
            "article_ressort_name": "\u00d6sterreich",
            "replies": [
              {
                "id": 1042159927,
                "parent_id": 1042159522,
                "user_id": 685775,
                "user_name": "mrs.robinson",
                "user_gender": "Unknown",
                "user_created_at": "2019-01-08T14:05:08.873000",
                "comment_headline": "No Headline",
                "comment_text": "Sie scheinen nicht zu wissen, dass heimlich gefilmtes Material vor Gericht als Beweismittel nicht zul\u00e4ssig ist und heimliches Filmen in Privatr\u00e4umen einen Straftatbestand darstellt.  Auf Ihre Unterstellung und den Versuch, mich politisch in ein Eck zu r\u00fccken, geh ich nicht ein. Das ist mir schlichtweg zu bl\u00f6d.",
                "comment_created_at": "2019-05-28T18:40:02.397000",
                "comment_length": 311,
                "article_id": 2000103960808,
                "article_publish_date": "2019-05-28T12:14:43",
                "article_title": "\"S\u00fcddeutsche Zeitung\" und \"Spiegel\" wegen Ibiza-Video angezeigt",
                "article_channel": "Panorama",
                "article_ressort_name": "\u00d6sterreich",
                "replies": [
                  {
                    "id": 1042160899,
                    "parent_id": 1042159927,
                    "user_id": 69463,
                    "user_name": "Gerry Mander",
                    "user_gender": "m",
                    "user_created_at": "2001-04-25T10:13:14",
                    "comment_headline": "es kommt immer drauf an",
                    "comment_text": "es sind sogar gestohlene daten, die der staat angekauft hat (das ist de facto hehlerei) als beweismittel anerkannt worden und die hehlerei wurde nicht geahndet.",
                    "comment_created_at": "2019-05-28T19:05:18.320000",
                    "comment_length": 160,
                    "article_id": 2000103960808,
                    "article_publish_date": "2019-05-28T12:14:43",
                    "article_title": "\"S\u00fcddeutsche Zeitung\" und \"Spiegel\" wegen Ibiza-Video angezeigt",
                    "article_channel": "Panorama",
                    "article_ressort_name": "\u00d6sterreich",
                    "replies": []
                  }
                ]
              }
            ]
          }
        ]
      }
    ]
  },
  "2000104040565": {
    "article_id": 2000104040565,
    "article_title": "Gr\u00f6\u00dftes Pokerkasino \u00d6sterreichs hat ausgespielt",
    "article_publish_date": "2019-05-29T14:34:57",
    "article_channel": "Wirtschaft",
    "article_ressort_name": "Insolvenzen",
    "total_comments": 146,
    "root_comments": 29,
    "user_threads": [
      {
        "id": 1042192368,
        "parent_id": 0,
        "user_id": 69463,
        "user_name": "Gerry Mander",
        "user_gender": "m",
        "user_created_at": "2001-04-25T10:13:14",
        "comment_headline": "ich dachte immer poker w\u00e4re ein geschicklichkeitsspiel",
        "comment_text": "und die sache w\u00e4re ausjudiziert gewesen?",
        "comment_created_at": "2019-05-29T15:24:35.423000",
        "comment_length": 40,
        "article_id": 2000104040565,
        "article_publish_date": "2019-05-29T14:34:57",
        "article_title": "Gr\u00f6\u00dftes Pokerkasino \u00d6sterreichs hat ausgespielt",
        "article_channel": "Wirtschaft",
        "article_ressort_name": "Insolvenzen",
        "replies": []
      }
    ]
  },
  "2000104060326": {
    "article_id": 2000104060326,
    "article_title": "Ausgeflogen: Red Bull stellt Air Race ein",
    "article_publish_date": "2019-05-29T18:10:16",
    "article_channel": "Sport",
    "article_ressort_name": "Motorsport ",
    "total_comments": 116,
    "root_comments": 42,
    "user_threads": [
      {
        "id": 1042216899,
        "parent_id": 0,
        "user_id": 159243,
        "user_name": "M-A-X",
        "user_gender": "m",
        "user_created_at": "2005-11-18T17:20:12.023000",
        "comment_headline": "No Headline",
        "comment_text": "es ist nie um einen echten sport gegangen...das ziel war also nur spektakel, dem volk gef\u00e4llt es nicht also wird es eingestellt.  wenn ich mir vorstelle dass jede sportart aufgel\u00f6st wird weils keinen interessiert.",
        "comment_created_at": "2019-05-30T08:06:10.040000",
        "comment_length": 213,
        "article_id": 2000104060326,
        "article_publish_date": "2019-05-29T18:10:16",
        "article_title": "Ausgeflogen: Red Bull stellt Air Race ein",
        "article_channel": "Sport",
        "article_ressort_name": "Motorsport ",
        "replies": [
          {
            "id": 1042218193,
            "parent_id": 1042216899,
            "user_id": 636045,
            "user_name": "sans.souci",
            "user_gender": "Unknown",
            "user_created_at": "2017-07-20T18:50:53.907000",
            "comment_headline": "No Headline",
            "comment_text": "das ziel war, den dosenumsatz zu steigern. vielleicht sponsert red bull ja demn\u00e4chst himalaya besteiger, die dann vom gipfel mit wingsuites zu tal ins basislager zur\u00fcckhuschen",
            "comment_created_at": "2019-05-30T09:17:34.550000",
            "comment_length": 175,
            "article_id": 2000104060326,
            "article_publish_date": "2019-05-29T18:10:16",
            "article_title": "Ausgeflogen: Red Bull stellt Air Race ein",
            "article_channel": "Sport",
            "article_ressort_name": "Motorsport ",
            "replies": [
              {
                "id": 1042229630,
                "parent_id": 1042218193,
                "user_id": 80661,
                "user_name": "Heavyweather",
                "user_gender": "m",
                "user_created_at": "2000-09-12T18:18:01",
                "comment_headline": "No Headline",
                "comment_text": "K\u00f6nnte man eigentlich mit dem Wingsuit vom Gipfel des Everest hupfen? Warum hat das noch keiner versucht?",
                "comment_created_at": "2019-05-30T14:36:54.070000",
                "comment_length": 105,
                "article_id": 2000104060326,
                "article_publish_date": "2019-05-29T18:10:16",
                "article_title": "Ausgeflogen: Red Bull stellt Air Race ein",
                "article_channel": "Sport",
                "article_ressort_name": "Motorsport ",
                "replies": [
                  {
                    "id": 1042244641,
                    "parent_id": 1042229630,
                    "user_id": 69463,
                    "user_name": "Gerry Mander",
                    "user_gender": "m",
                    "user_created_at": "2001-04-25T10:13:14",
                    "comment_headline": "irgendwann wird ihnen eh nichts anderes \u00fcbrig bleiben",
                    "comment_text": "weil der r\u00fcckweg ja anscheinend permanent verstopft ist. spring oder stirb!",
                    "comment_created_at": "2019-05-30T21:14:17.080000",
                    "comment_length": 75,
                    "article_id": 2000104060326,
                    "article_publish_date": "2019-05-29T18:10:16",
                    "article_title": "Ausgeflogen: Red Bull stellt Air Race ein",
                    "article_channel": "Sport",
                    "article_ressort_name": "Motorsport ",
                    "replies": []
                  }
                ]
              }
            ]
          }
        ]
      }
    ]
  },
  "2000104097812": {
    "article_id": 2000104097812,
    "article_title": "OECD: Hochqualifizierte wollen nicht nach \u00d6sterreich",
    "article_publish_date": "2019-05-30T17:40:57",
    "article_channel": "Wirtschaft",
    "article_ressort_name": "Wirtschaftspolitik",
    "total_comments": 699,
    "root_comments": 164,
    "user_threads": [
      {
        "id": 1042244080,
        "parent_id": 0,
        "user_id": 69463,
        "user_name": "Gerry Mander",
        "user_gender": "m",
        "user_created_at": "2001-04-25T10:13:14",
        "comment_headline": "ich kann in diesem kontext die mercer studie nicht richtig einordnen",
        "comment_text": "f\u00fcr expats scheint wien die beste stadt der welt zum leben zu sein, aber eigentlich will keiner dort arbeiten?",
        "comment_created_at": "2019-05-30T20:52:34.703000",
        "comment_length": 110,
        "article_id": 2000104097812,
        "article_publish_date": "2019-05-30T17:40:57",
        "article_title": "OECD: Hochqualifizierte wollen nicht nach \u00d6sterreich",
        "article_channel": "Wirtschaft",
        "article_ressort_name": "Wirtschaftspolitik",
        "replies": [
          {
            "id": 1042244480,
            "parent_id": 1042244080,
            "user_id": 655196,
            "user_name": "echtwirklich",
            "user_gender": "Unknown",
            "user_created_at": "2017-12-28T10:36:05.427000",
            "comment_headline": "No Headline",
            "comment_text": "Die Mercer-Studie zielt ja auf ins Ausland entsendete Mitarbeiter (Expats). Diese Besch\u00e4ftigungen sind oft auf 3 Jahre befristet und die Leute m\u00f6chten auch nicht wirklich die deutsche Sprache lernen, sondern danach weiterziehen und die \"internationale\" Infrastruktur nutzen. Es ist ein Unterschied, wenn sich die Bewerber alles selbst organisieren m\u00fcssen (nicht durch die Firma), integrieren m\u00f6chten, und wenn sie auch l\u00e4nger da bleiben m\u00f6chten, da sind die rassistische Anp\u00f6belungen schon eher ein Thema.",
            "comment_created_at": "2019-05-30T21:06:59.700000",
            "comment_length": 505,
            "article_id": 2000104097812,
            "article_publish_date": "2019-05-30T17:40:57",
            "article_title": "OECD: Hochqualifizierte wollen nicht nach \u00d6sterreich",
            "article_channel": "Wirtschaft",
            "article_ressort_name": "Wirtschaftspolitik",
            "replies": [
              {
                "id": 1042307082,
                "parent_id": 1042244480,
                "user_id": 69463,
                "user_name": "Gerry Mander",
                "user_gender": "m",
                "user_created_at": "2001-04-25T10:13:14",
                "comment_headline": "ja, das leuchtet mir ein",
                "comment_text": "in den klassischen einwanderungsl\u00e4ndern (USA, Canada, Australien) werden sie ja von tag eins an versorgt. und dort wird auch niemand rassistisch angep\u00f6belt.",
                "comment_created_at": "2019-06-01T23:56:28.417000",
                "comment_length": 156,
                "article_id": 2000104097812,
                "article_publish_date": "2019-05-30T17:40:57",
                "article_title": "OECD: Hochqualifizierte wollen nicht nach \u00d6sterreich",
                "article_channel": "Wirtschaft",
                "article_ressort_name": "Wirtschaftspolitik",
                "replies": []
              }
            ]
          }
        ]
      }
    ]
  }
}